krxholidays/__init__.py
krxholidays/data.py
krx_holidays-0.0.3.dist-info/LICENSE
krx_holidays-0.0.3.dist-info/METADATA
krx_holidays-0.0.3.dist-info/WHEEL
krx_holidays-0.0.3.dist-info/top_level.txt
krx_holidays-0.0.3.dist-info/RECORD
