Metadata-Version: 2.1
Name: krx-holidays
Version: 0.0.3
Summary: KRX Holidays
Home-page: https://github.com/cheddars/krx_holidays
Author: cheddars
Author-email: nezahrish@gmail.com
License: MIT
Platform: UNKNOWN
Classifier: Programming Language :: Python :: 3
Classifier: License :: OSI Approved :: MIT License
Classifier: Operating System :: OS Independent
License-File: LICENSE
